CHANGES.txt
setup.py
Products/__init__.py
Products.errornumber.egg-info/PKG-INFO
Products.errornumber.egg-info/SOURCES.txt
Products.errornumber.egg-info/dependency_links.txt
Products.errornumber.egg-info/namespace_packages.txt
Products.errornumber.egg-info/not-zip-safe
Products.errornumber.egg-info/requires.txt
Products.errornumber.egg-info/top_level.txt
Products/errornumber/__init__.py
Products/errornumber/version.txt