Metadata-Version: 1.0
Name: Products.errornumber
Version: 1.2
Summary: Patch error_log to also log the error number.
Home-page: http://pypi.python.org/pypi/Products.errornumber
Author: Stefan H. Holek
Author-email: stefan@epy.co.at
License: ZPL
Platform: UNKNOWN
Classifier: Framework :: Zope2
Classifier: Programming Language :: Python
Classifier: Topic :: Software Development :: Libraries :: Python Modules
